Workbook
Name M: #REF!
Name MTHREE: #REF!
Name MTWO: #REF!

Sheet merton 
A1: Merton model
B2: Iteration 1 | C2: Iteration 2 | D2: Iteration 3 | E2: Iteration 4 | F2: Iteration 5
A3: Interest rate | B3: =O11 -> 0.0296991 | C3: =B3 -> 0.0296991 | D3: =C3 -> 0.0296991 | E3: =D3 -> 0.0296991 | F3: 0.0314247 | G3: input from Assignment 1 for zero coupon on Jan 5
A4: Book value, bn | B4: 218.973 | C4: =B4 -> 218.973 | D4: =C4 -> 218.973 | E4: =D4 -> 218.973 | F4: =E4 -> 218.973 | G4: input from the financial statement | N4: Interest rate | O4: 0.0314247
A5: Time to maturity | B5: 1 | C5: =B5 -> 1 | D5: =C5 -> 1 | E5: =D5 -> 1 | F5: =E5 -> 1 | G5: manual input | N5: Book value, bn | O5: 218.973
A6: Exercise price, K=L, bn | B6: =150*(1+B3)^B5 -> 154.45486 | C6: =B6 -> 154.45486 | D6: =C6 -> 154.45486 | E6: =D6 -> 154.45486 | F6: =E6 -> 154.45486 | G6: strike price is equal to the value of debt multiplied by (1+r)^n | N6: Time to maturity
A7: Sigma s, percent | B7: 0.2966 | C7: 0.2966 | D7: 0.2966 | E7: 0.2966 | F7: 0.2966 | G7: stock volatility, annual average | N7: Exercise price, K=L, bn | O7: 150
A8: Sigma a, percent | B8: =B7 -> 0.2966 | C8: =B11 -> 0.10505977 | D8: =C11 -> 0.093525009 | E8: =D11 -> 0.093514209 | F8: =E11 -> 0.093514205 | G8: to start iteration, it is set as equal to sigma s in Iteration 1 | N8: Sigma s, percent | O8: =29.66*0.01 -> 0.2966
A9: Option price, S | B9: =B4*NORMSDIST(B14)-B6*EXP(-B3*B5)*NORMSDIST(B15) -> 71.587648 | C9: =C4*NORMSDIST(C14)-C6*EXP(-C3*C5)*NORMSDIST(C15) -> 69.038586 | D9: =D4*NORMSDIST(D14)-D6*EXP(-D3*D5)*NORMSDIST(D15) -> 69.037954 | E9: =E4*NORMSDIST(E14)-E6*EXP(-E3*E5)*NORMSDIST(E15) -> 69.037954 | F9: =F4*NORMSDIST(F14)-F6*EXP(-F3*F5)*NORMSDIST(F15) -> 69.296451 | G9: calculated
A10: Option delta | B10: =NORMSDIST(B14) -> 0.92295862 | C10: =NORMSDIST(C14) -> 0.9998727 | D10: =NORMSDIST(D14) -> 0.99997902 | E10: =NORMSDIST(E14) -> 0.99997906 | F10: =NORMSDIST(F14) -> 0.99998067 | G10: calculated | N10: Maturity (31 st of December) | O10: Canadian Treasury Yields
A11: Fixed point (sigmas*S)/(V*delta) | B11: =(B7*B9)/(B4*B10) -> 0.10505977 | C11: =(C7*C9)/(C4*C10) -> 0.093525009 | D11: =(D7*D9)/(D4*D10) -> 0.093514209 | E11: =(E7*E9)/(E4*E10) -> 0.093514205 | F11: =(F7*F9)/(F4*F10) -> 0.093864197 | G11: calculated | N11: 2026 | O11: 0.0296991
N12: 2027 | O12: 0.0286496
N13: 2028 | O13: 0.0285297
A14: d1 | B14: =(LN(B4/B6)+(B3+0.5*B8^2)*B5)/(B8*SQRT(B5)) -> 1.4252576 | C14: =(LN(C4/C6)+(C3+0.5*C8^2)*C5)/(C8*SQRT(C5)) -> 3.6575789 | D14: =(LN(D4/D6)+(D3+0.5*D8^2)*D5)/(D8*SQRT(D5)) -> 4.0964346 | E14: =(LN(E4/E6)+(E3+0.5*E8^2)*E5)/(E8*SQRT(E5)) -> 4.0968969 | F14: =(LN(F4/F6)+(F3+0.5*F8^2)*F5)/(F8*SQRT(F5)) -> 4.1153499 | N14: 2029 | O14: 0.0289418
A15: d2 | B15: =B14-B8*SQRT(B5) -> 1.1286576 | C15: =C14-C8*SQRT(C5) -> 3.5525191 | D15: =D14-D8*SQRT(D5) -> 4.0029096 | E15: =E14-E8*SQRT(E5) -> 4.0033827 | F15: =F14-F8*SQRT(F5) -> 4.0218357 | N15: 2030 | O15: 0.0295897
A16: BV-L | B16: =B4-B6 -> 64.518135 | C16: =C4-C6 -> 64.518135 | D16: =D4-D6 -> 64.518135 | E16: =E4-E6 -> 64.518135 | F16: =F4-F6 -> 64.518135 | N16: 2031 | O16: 0.0302938
N17: 2032 | O17: 0.0309537
A18: Probability of default=N(-d2) | F18: =1-NORMSDIST(F15) -> 2.8873171e-05 | N18: 2033 | O18: 0.0315206
N19: 2034 | O19: 0.0319782
B20: Iteration 1 | C20: Iteration 2 | D20: Iteration 3 | E20: Iteration 4 | F20: Iteration 5 | N20: 2035 | O20: 0.0323294
A21: Interest rate | B21: =$O$12 -> 0.0286496 | C21: =$O$12 -> 0.0286496 | D21: =$O$12 -> 0.0286496 | E21: =$O$12 -> 0.0286496 | F21: 0.0314247 | G21: input from Assignment 1 for zero coupon on Jan 5
A22: Book value, bn | B22: 218.973 | C22: =B22 -> 218.973 | D22: =C22 -> 218.973 | E22: =D22 -> 218.973 | F22: =E22 -> 218.973 | G22: input from the financial statement
A23: Time to maturity | B23: 2 | C23: =B23 -> 2 | D23: =C23 -> 2 | E23: =D23 -> 2 | F23: =E23 -> 2 | G23: manual input
A24: Exercise price, K=L, bn | B24: =150*(1+B21)^B23 -> 158.718 | C24: =B24 -> 158.718 | D24: =C24 -> 158.718 | E24: =D24 -> 158.718 | F24: =E24 -> 158.718 | G24: strike price is equal to the value of debt multiplied by (1+r)^n
A25: Sigma s, percent | B25: 0.2966 | C25: 0.2966 | D25: 0.2966 | E25: 0.2966 | F25: 0.2966 | G25: stock volatility, annual average
A26: Sigma a, percent | B26: =B25 -> 0.2966 | C26: =B29 -> 0.1195884 | D26: =C29 -> 0.094714787 | E26: =D29 -> 0.093786868 | F26: =E29 -> 0.093769804 | G26: to start iteration, it is set as equal to sigma s in Iteration 1
A27: Option price, S | B27: =B22*NORMSDIST(B32)-B24*EXP(-B21*B23)*NORMSDIST(B33) -> 76.570425 | C27: =C22*NORMSDIST(C32)-C24*EXP(-C21*C23)*NORMSDIST(C33) -> 69.226282 | D27: =D22*NORMSDIST(D32)-D24*EXP(-D21*D23)*NORMSDIST(D33) -> 69.110409 | E27: =E22*NORMSDIST(E32)-E24*EXP(-E21*E23)*NORMSDIST(E33) -> 69.108752 | F27: =F22*NORMSDIST(F32)-F24*EXP(-F21*F23)*NORMSDIST(F33) -> 69.936244 | G27: calculated
A28: Option delta | B28: =NORMSDIST(B32) -> 0.86726652 | C28: =NORMSDIST(C32) -> 0.98999682 | D28: =NORMSDIST(D32) -> 0.99811828 | E28: =NORMSDIST(E32) -> 0.99827597 | F28: =NORMSDIST(F32) -> 0.99849662 | G28: calculated
A29: Fixed point (sigmas*S)/(V*delta) | B29: =(B25*B27)/(B22*B28) -> 0.1195884 | C29: =(C25*C27)/(C22*C28) -> 0.094714787 | D29: =(D25*D27)/(D22*D28) -> 0.093786868 | E29: =(E25*E27)/(E22*E28) -> 0.093769804 | F29: =(F25*F27)/(F22*F28) -> 0.094871613 | G29: calculated
A32: d1 | B32: =(LN(B22/B24)+(B21+0.5*B26^2)*B23)/(B26*SQRT(B23)) -> 1.1135624 | C32: =(LN(C22/C24)+(C21+0.5*C26^2)*C23)/(C26*SQRT(C23)) -> 2.3262284 | D32: =(LN(D22/D24)+(D21+0.5*D26^2)*D23)/(D26*SQRT(D23)) -> 2.8973375 | E32: =(LN(E22/E24)+(E21+0.5*E26^2)*E23)/(E26*SQRT(E23)) -> 2.9246847 | F32: =(LN(F22/F24)+(F21+0.5*F26^2)*F23)/(F26*SQRT(F23)) -> 2.9670462
A33: d2 | B33: =B32-B26*SQRT(B23) -> 0.69410668 | C33: =C32-C26*SQRT(C23) -> 2.1571049 | D33: =D32-D26*SQRT(D23) -> 2.7633906 | E33: =E32-E26*SQRT(E23) -> 2.7920501 | F33: =F32-F26*SQRT(F23) -> 2.8344357
A34: BV-L | B34: =B22-B24 -> 60.255 | C34: =C22-C24 -> 60.255 | D34: =D22-D24 -> 60.255 | E34: =E22-E24 -> 60.255 | F34: =F22-F24 -> 60.255
A36: Probability of default=N(-d2) | F36: =1-NORMSDIST(F33) -> 0.0022953348
B38: Iteration 1 | C38: Iteration 2 | D38: Iteration 3 | E38: Iteration 4 | F38: Iteration 5
A39: Interest rate | B39: =$O$13 -> 0.0285297 | C39: =$O$13 -> 0.0285297 | D39: =$O$13 -> 0.0285297 | E39: =$O$13 -> 0.0285297 | F39: 0.0314247 | G39: input from Assignment 1 for zero coupon on Jan 5
A40: Book value, bn | B40: 218.973 | C40: =B40 -> 218.973 | D40: =C40 -> 218.973 | E40: =D40 -> 218.973 | F40: =E40 -> 218.973 | G40: input from the financial statement
A41: Time to maturity | B41: 3 | C41: =B41 -> 3 | D41: =C41 -> 3 | E41: =D41 -> 3 | F41: =E41 -> 3 | G41: manual input
A42: Exercise price, K=L, bn | B42: =150*(1+B39)^B41 -> 163.20812 | C42: =B42 -> 163.20812 | D42: =C42 -> 163.20812 | E42: =D42 -> 163.20812 | F42: =E42 -> 163.20812 | G42: strike price is equal to the value of debt multiplied by (1+r)^n
A43: Sigma s, percent | B43: 0.2966 | C43: 0.2966 | D43: 0.2966 | E43: 0.2966 | F43: 0.2966 | G43: stock volatility, annual average
A44: Sigma a, percent | B44: =B43 -> 0.2966 | C44: =B47 -> 0.13115532 | D44: =C47 -> 0.098417438 | E44: =D47 -> 0.094842993 | F44: =E47 -> 0.09460215 | G44: to start iteration, it is set as equal to sigma s in Iteration 1
A45: Option price, S | B45: =B40*NORMSDIST(B50)-B42*EXP(-B39*B41)*NORMSDIST(B51) -> 81.363358 | C45: =C40*NORMSDIST(C50)-C42*EXP(-C39*C41)*NORMSDIST(C51) -> 69.956772 | D45: =D40*NORMSDIST(D50)-D42*EXP(-D39*D41)*NORMSDIST(D51) -> 69.292162 | E45: =E40*NORMSDIST(E50)-E42*EXP(-E39*E41)*NORMSDIST(E51) -> 69.258049 | F45: =F40*NORMSDIST(F50)-F42*EXP(-F39*F41)*NORMSDIST(F51) -> 70.536121 | G45: calculated
A46: Option delta | B46: =NORMSDIST(B50) -> 0.84027905 | C46: =NORMSDIST(C50) -> 0.96280489 | D46: =NORMSDIST(D50) -> 0.98959944 | E46: =NORMSDIST(E50) -> 0.99163038 | F46: =NORMSDIST(F50) -> 0.99287824 | G46: calculated
A47: Fixed point (sigmas*S)/(V*delta) | B47: =(B43*B45)/(B40*B46) -> 0.13115532 | C47: =(C43*C45)/(C40*C46) -> 0.098417438 | D47: =(D43*D45)/(D40*D46) -> 0.094842993 | E47: =(E43*E45)/(E40*E46) -> 0.09460215 | F47: =(F43*F45)/(F40*F46) -> 0.096226825 | G47: calculated
A50: d1 | B50: =(LN(B40/B42)+(B39+0.5*B44^2)*B41)/(B44*SQRT(B41)) -> 0.99560542 | C50: =(LN(C40/C42)+(C39+0.5*C44^2)*C41)/(C44*SQRT(C41)) -> 1.7842059 | D50: =(LN(D40/D42)+(D39+0.5*D44^2)*D41)/(D44*SQRT(D41)) -> 2.3115749 | E50: =(LN(E40/E42)+(E39+0.5*E44^2)*E41)/(E44*SQRT(E41)) -> 2.3923858 | F50: =(LN(F40/F42)+(F39+0.5*F44^2)*F41)/(F44*SQRT(F41)) -> 2.4510627
A51: d2 | B51: =B50-B44*SQRT(B41) -> 0.48187915 | C51: =C50-C44*SQRT(C41) -> 1.5570382 | D51: =D50-D44*SQRT(D41) -> 2.1411109 | E51: =E50-E44*SQRT(E41) -> 2.2281129 | F51: =F50-F44*SQRT(F41) -> 2.287207
A52: BV-L | B52: =B40-B42 -> 55.764877 | C52: =C40-C42 -> 55.764877 | D52: =D40-D42 -> 55.764877 | E52: =E40-E42 -> 55.764877 | F52: =F40-F42 -> 55.764877
A54: Probability of default=N(-d2) | F54: =1-NORMSDIST(F51) -> 0.011091873
B56: Iteration 1 | C56: Iteration 2 | D56: Iteration 3 | E56: Iteration 4 | F56: Iteration 5
A57: Interest rate | B57: =$O$14 -> 0.0289418 | C57: =$O$14 -> 0.0289418 | D57: =$O$14 -> 0.0289418 | E57: =$O$14 -> 0.0289418 | F57: 0.0314247 | G57: input from Assignment 1 for zero coupon on Jan 5
A58: Book value, bn | B58: 218.973 | C58: =B58 -> 218.973 | D58: =C58 -> 218.973 | E58: =D58 -> 218.973 | F58: =E58 -> 218.973 | G58: input from the financial statement
A59: Time to maturity | B59: 4 | C59: =B59 -> 4 | D59: =C59 -> 4 | E59: =D59 -> 4 | F59: =E59 -> 4 | G59: manual input
A60: Exercise price, K=L, bn | B60: =150*(1+ B57)^B59 -> 168.1336 | C60: =B60 -> 168.1336 | D60: =C60 -> 168.1336 | E60: =D60 -> 168.1336 | F60: =E60 -> 168.1336 | G60: strike price is equal to the value of debt multiplied by (1+r)^n
A61: Sigma s, percent | B61: 0.2966 | C61: 0.2966 | D61: 0.2966 | E61: 0.2966 | F61: 0.2966 | G61: stock volatility, annual average
A62: Sigma a, percent | B62: =B61 -> 0.2966 | C62: =B65 -> 0.14070761 | D62: =C65 -> 0.10360536 | E62: =D65 -> 0.096977391 | F62: =E65 -> 0.096118857 | G62: to start iteration, it is set as equal to sigma s in Iteration 1
A63: Option price, S | B63: =B58*NORMSDIST(B68)-B60*EXP(-B57*B59)*NORMSDIST(B69) -> 85.769702 | C63: =C58*NORMSDIST(C68)-C60*EXP(-C57*C59)*NORMSDIST(C69) -> 71.288371 | D63: =D58*NORMSDIST(D68)-D60*EXP(-D57*D59)*NORMSDIST(D69) -> 69.709227 | E63: =E58*NORMSDIST(E68)-E60*EXP(-E57*E59)*NORMSDIST(E69) -> 69.550735 | F63: =F58*NORMSDIST(F68)-F60*EXP(-F57*F59)*NORMSDIST(F69) -> 70.970928 | G63: calculated
A64: Option delta | B64: =NORMSDIST(B68) -> 0.82565171 | C64: =NORMSDIST(C68) -> 0.93200242 | D64: =NORMSDIST(D68) -> 0.97364435 | E64: =NORMSDIST(E68) -> 0.98010749 | F64: =NORMSDIST(F68) -> 0.98317648 | G64: calculated
A65: Fixed point (sigmas*S)/(V*delta) | B65: =(B61*B63)/(B58*B64) -> 0.14070761 | C65: =(C61*C63)/(C58*C64) -> 0.10360536 | D65: =(D61*D63)/(D58*D64) -> 0.096977391 | E65: =(E61*E63)/(E58*E64) -> 0.096118857 | F65: =(F61*F63)/(F58*F64) -> 0.097775396 | G65: calculated
A68: d1 | B68: =(LN(B58/B60)+(B57+0.5*B62^2)*B59)/(B62*SQRT(B59)) -> 0.9371205 | C68: =(LN(C58/C60)+(C57+0.5*C62^2)*C59)/(C62*SQRT(C59)) -> 1.4908718 | D68: =(LN(D58/D60)+(D57+0.5*D62^2)*D59)/(D62*SQRT(D59)) -> 1.9372786 | E68: =(LN(E58/E60)+(E57+0.5*E62^2)*E59)/(E62*SQRT(E59)) -> 2.055974 | F68: =(LN(F58/F60)+(F57+0.5*F62^2)*F59)/(F62*SQRT(F59)) -> 2.1242763
A69: d2 | B69: =B68-B62*SQRT(B59) -> 0.3439205 | C69: =C68-C62*SQRT(C59) -> 1.2094566 | D69: =D68-D62*SQRT(D59) -> 1.7300679 | E69: =E68-E62*SQRT(E59) -> 1.8620192 | F69: =F68-F62*SQRT(F59) -> 1.9320386
A70: BV-L | B70: =B58-B60 -> 50.839404 | C70: =C58-C60 -> 50.839404 | D70: =D58-D60 -> 50.839404 | E70: =E58-E60 -> 50.839404 | F70: =F58-F60 -> 50.839404
A72: Probability of default=N(-d2) | F72: =1-NORMSDIST(F69) -> 0.026677369
B74: Iteration 1 | C74: Iteration 2 | D74: Iteration 3 | E74: Iteration 4 | F74: Iteration 5
A75: Interest rate | B75: =$O$15 -> 0.0295897 | C75: =$O$15 -> 0.0295897 | D75: =$O$15 -> 0.0295897 | E75: =$O$15 -> 0.0295897 | F75: 0.0314247 | G75: input from Assignment 1 for zero coupon on Jan 5
A76: Book value, bn | B76: 218.973 | C76: =B76 -> 218.973 | D76: =C76 -> 218.973 | E76: =D76 -> 218.973 | F76: =E76 -> 218.973 | G76: input from the financial statement
A77: Time to maturity | B77: 5 | C77: =B77 -> 5 | D77: =C77 -> 5 | E77: =D77 -> 5 | F77: =E77 -> 5 | G77: manual input
A78: Exercise price, K=L, bn | B78: =150*(1+B75)^B77 -> 173.54504 | C78: =B78 -> 173.54504 | D78: =C78 -> 173.54504 | E78: =D78 -> 173.54504 | F78: =E78 -> 173.54504 | G78: strike price is equal to the value of debt multiplied by (1+r)^n
A79: Sigma s, percent | B79: 0.2966 | C79: 0.2966 | D79: 0.2966 | E79: 0.2966 | F79: 0.2966 | G79: stock volatility, annual average
A80: Sigma a, percent | B80: =B79 -> 0.2966 | C80: =B83 -> 0.14885473 | D80: =C83 -> 0.10936357 | E80: =D83 -> 0.10006708 | F80: =E83 -> 0.098296005 | G80: to start iteration, it is set as equal to sigma s in Iteration 1
A81: Option price, S | B81: =B76*NORMSDIST(B86)-B78*EXP(-B75*B77)*NORMSDIST(B87) -> 89.822194 | C81: =C76*NORMSDIST(C86)-C78*EXP(-C75*C77)*NORMSDIST(C87) -> 73.055036 | D81: =D76*NORMSDIST(D86)-D78*EXP(-D75*D77)*NORMSDIST(D87) -> 70.429577 | E81: =E76*NORMSDIST(E86)-E78*EXP(-E75*E77)*NORMSDIST(E87) -> 70.031408 | F81: =F76*NORMSDIST(F86)-F78*EXP(-F75*F77)*NORMSDIST(F87) -> 71.264377 | G81: calculated
A82: Option delta | B82: =NORMSDIST(B86) -> 0.81733783 | C82: =NORMSDIST(C86) -> 0.90481135 | D82: =NORMSDIST(D86) -> 0.95333255 | E82: =NORMSDIST(E86) -> 0.96502278 | F82: =NORMSDIST(F86) -> 0.97012303 | G82: calculated
A83: Fixed point (sigmas*S)/(V*delta) | B83: =(B79*B81)/(B76*B82) -> 0.14885473 | C83: =(C79*C81)/(C76*C82) -> 0.10936357 | D83: =(D79*D81)/(D76*D82) -> 0.10006708 | E83: =(E79*E81)/(E76*E82) -> 0.098296005 | F83: =(F79*F81)/(F76*F82) -> 0.099500728 | G83: calculated
A86: d1 | B86: =(LN(B76/B78)+(B75+0.5*B80^2)*B77)/(B80*SQRT(B77)) -> 0.90526628 | C86: =(LN(C76/C78)+(C75+0.5*C80^2)*C77)/(C80*SQRT(C77)) -> 1.3094638 | D86: =(LN(D76/D78)+(D75+0.5*D80^2)*D77)/(D80*SQRT(D77)) -> 1.6780625 | E86: =(LN(E76/E78)+(E75+0.5*E80^2)*E77)/(E80*SQRT(E77)) -> 1.8122056 | F86: =(LN(F76/F78)+(F75+0.5*F80^2)*F77)/(F80*SQRT(F77)) -> 1.8826048
A87: d2 | B87: =B86-B80*SQRT(B77) -> 0.24204851 | C87: =C86-C80*SQRT(C77) -> 0.97661451 | D87: =D86-D80*SQRT(D77) -> 1.4335181 | E87: =E86-E80*SQRT(E77) -> 1.5884488 | F87: =F86-F80*SQRT(F77) -> 1.6628082
A88: BV-L | B88: =B76-B78 -> 45.42796 | C88: =C76-C78 -> 45.42796 | D88: =D76-D78 -> 45.42796 | E88: =E76-E78 -> 45.42796 | F88: =F76-F78 -> 45.42796
A90: Probability of default=N(-d2) | F90: =1-NORMSDIST(F87) -> 0.048175415
B92: Iteration 1 | C92: Iteration 2 | D92: Iteration 3 | E92: Iteration 4 | F92: Iteration 5
A93: Interest rate | B93: =$O$16 -> 0.0302938 | C93: =$O$16 -> 0.0302938 | D93: =$O$16 -> 0.0302938 | E93: =$O$16 -> 0.0302938 | F93: =$O$16 -> 0.0302938 | G93: input from Assignment 1 for zero coupon on Jan 5
A94: Book value, bn | B94: 218.973 | C94: =B94 -> 218.973 | D94: =C94 -> 218.973 | E94: =D94 -> 218.973 | F94: =E94 -> 218.973 | G94: input from the financial statement
A95: Time to maturity | B95: 6 | C95: =B95 -> 6 | D95: =C95 -> 6 | E95: =D95 -> 6 | F95: =E95 -> 6 | G95: manual input
A96: Exercise price, K=L, bn | B96: =150*(1+B93)^B95 -> 179.4146 | C96: =B96 -> 179.4146 | D96: =C96 -> 179.4146 | E96: =D96 -> 179.4146 | F96: =E96 -> 179.4146 | G96: strike price is equal to the value of debt multiplied by (1+r)^n
A97: Sigma s, percent | B97: 0.2966 | C97: 0.2966 | D97: 0.2966 | E97: 0.2966 | F97: 0.2966 | G97: stock volatility, annual average
A98: Sigma a, percent | B98: =B97 -> 0.2966 | C98: =B101 -> 0.15596479 | D98: =C101 -> 0.11524898 | E98: =D101 -> 0.10384672 | F98: =E101 -> 0.10106057 | G98: to start iteration, it is set as equal to sigma s in Iteration 1
A99: Option price, S | B99: =B94*NORMSDIST(B104)-B96*EXP(-B93*B95)*NORMSDIST(B105) -> 93.572485 | C99: =C94*NORMSDIST(C104)-C96*EXP(-C93*C95)*NORMSDIST(C105) -> 75.100924 | D99: =D94*NORMSDIST(D104)-D96*EXP(-D93*D95)*NORMSDIST(D105) -> 71.453876 | E99: =E94*NORMSDIST(E104)-E96*EXP(-E93*E95)*NORMSDIST(E105) -> 70.725223 | F99: =F94*NORMSDIST(F104)-F96*EXP(-F93*F95)*NORMSDIST(F105) -> 70.570812 | G99: calculated
A100: Option delta | B100: =NORMSDIST(B104) -> 0.81264744 | C100: =NORMSDIST(C104) -> 0.88265051 | D100: =NORMSDIST(D104) -> 0.93199499 | E100: =NORMSDIST(E104) -> 0.94792319 | F100: =NORMSDIST(F104) -> 0.9518362 | G100: calculated
A101: Fixed point (sigmas*S)/(V*delta) | B101: =(B97*B99)/(B94*B100) -> 0.15596479 | C101: =(C97*C99)/(C94*C100) -> 0.11524898 | D101: =(D97*D99)/(D94*D100) -> 0.10384672 | E101: =(E97*E99)/(E94*E100) -> 0.10106057 | F101: =(F97*F99)/(F94*F100) -> 0.10042538 | G101: calculated
A104: d1 | B104: =(LN(B94/B96)+(B93+0.5*B98^2)*B95)/(B98*SQRT(B95)) -> 0.88769447 | C104: =(LN(C94/C96)+(C93+0.5*C98^2)*C95)/(C98*SQRT(C95)) -> 1.1883413 | D104: =(LN(D94/D96)+(D93+0.5*D98^2)*D95)/(D98*SQRT(D95)) -> 1.4908152 | E104: =(LN(E94/E96)+(E93+0.5*E98^2)*E95)/(E98*SQRT(E95)) -> 1.625042 | F104: =(LN(F94/F96)+(F93+0.5*F98^2)*F95)/(F98*SQRT(F95)) -> 1.6629242
A105: d2 | B105: =B104-B98*SQRT(B95) -> 0.16117581 | C105: =C104-C98*SQRT(C95) -> 0.80630713 | D105: =D104-D98*SQRT(D95) -> 1.208514 | E105: =E104-E98*SQRT(E95) -> 1.3706705 | F105: =F104-F98*SQRT(F95) -> 1.4153774
A106: BV-L | B106: =B94-B96 -> 39.558402 | C106: =C94-C96 -> 39.558402 | D106: =D94-D96 -> 39.558402 | E106: =E94-E96 -> 39.558402 | F106: =F94-F96 -> 39.558402
A108: Probability of default=N(-d2) | F108: =1-NORMSDIST(F105) -> 0.078478937
B110: Iteration 1 | C110: Iteration 2 | D110: Iteration 3 | E110: Iteration 4 | F110: Iteration 5
A111: Interest rate | B111: =$O$17 -> 0.0309537 | C111: =$O$17 -> 0.0309537 | D111: =$O$17 -> 0.0309537 | E111: =$O$17 -> 0.0309537 | F111: =$O$17 -> 0.0309537 | G111: input from Assignment 1 for zero coupon on Jan 5
A112: Book value, bn | B112: 218.973 | C112: =B112 -> 218.973 | D112: =C112 -> 218.973 | E112: =D112 -> 218.973 | F112: =E112 -> 218.973 | G112: input from the financial statement
A113: Time to maturity | B113: 7 | C113: =B113 -> 7 | D113: =C113 -> 7 | E113: =D113 -> 7 | F113: =E113 -> 7 | G113: manual input
A114: Exercise price, K=L, bn | B114: =150*(1+B111)^B113 -> 185.68011 | C114: =B114 -> 185.68011 | D114: =C114 -> 185.68011 | E114: =D114 -> 185.68011 | F114: =E114 -> 185.68011 | G114: strike price is equal to the value of debt multiplied by (1+r)^n
A115: Sigma s, percent | B115: 0.2966 | C115: 0.2966 | D115: 0.2966 | E115: 0.2966 | F115: 0.2966 | G115: stock volatility, annual average
A116: Sigma a, percent | B116: =B115 -> 0.2966 | C116: =B119 -> 0.16227459 | D116: =C119 -> 0.12105835 | E116: =D119 -> 0.10807253 | F116: =E119 -> 0.10430993 | G116: to start iteration, it is set as equal to sigma s in Iteration 1
A117: Option price, S | B117: =B112*NORMSDIST(B122)-B114*EXP(-B111*B113)*NORMSDIST(B123) -> 97.065288 | C117: =C112*NORMSDIST(C122)-C114*EXP(-C111*C113)*NORMSDIST(C123) -> 77.31707 | D117: =D112*NORMSDIST(D122)-D114*EXP(-D111*D113)*NORMSDIST(D123) -> 72.745607 | E117: =E112*NORMSDIST(E122)-E114*EXP(-E111*E113)*NORMSDIST(E123) -> 71.637037 | F117: =F112*NORMSDIST(F122)-F114*EXP(-F111*F113)*NORMSDIST(F123) -> 71.354188 | G117: calculated
A118: Option delta | B118: =NORMSDIST(B122) -> 0.81020327 | C118: =NORMSDIST(C122) -> 0.86508985 | D118: =NORMSDIST(D122) -> 0.91174212 | E118: =NORMSDIST(E122) -> 0.93023467 | F118: =NORMSDIST(F122) -> 0.93583287 | G118: calculated
A119: Fixed point (sigmas*S)/(V*delta) | B119: =(B115*B117)/(B112*B118) -> 0.16227459 | C119: =(C115*C117)/(C112*C118) -> 0.12105835 | D119: =(D115*D117)/(D112*D118) -> 0.10807253 | E119: =(E115*E117)/(E112*E118) -> 0.10430993 | F119: =(F115*F117)/(F112*F118) -> 0.10327656 | G119: calculated
A122: d1 | B122: =(LN(B112/B114)+(B111+0.5*B116^2)*B113)/(B116*SQRT(B113)) -> 0.87864561 | C122: =(LN(C112/C114)+(C111+0.5*C116^2)*C113)/(C116*SQRT(C113)) -> 1.1034765 | D122: =(LN(D112/D114)+(D111+0.5*D116^2)*D113)/(D116*SQRT(D113)) -> 1.3515611 | E122: =(LN(E112/E114)+(E111+0.5*E116^2)*E113)/(E116*SQRT(E113)) -> 1.4775411 | F122: =(LN(F112/F114)+(F111+0.5*F116^2)*F113)/(F116*SQRT(F113)) -> 1.5207035
...

Sheet creadit metric
D6: Maturity Date | E6: US Treasury (%) | F6: Enbridge Bond Yield in USD (%) | G6: Spread (%)
D7: =DATE(2026,11,15) -> 46341 | E7: =0.04245*100% -> 0.04245 | F7: 0.049216982 | G7: =F7-E7 -> 0.0067669815
D8: =DATE(2027,4,5) -> 46482 | E8: =0.04245*100% -> 0.04245 | F8: 0.048045307 | G8: =F8-E8 -> 0.0055953066
D9: =DATE(2028,5,15) -> 46888 | E9: =0.042535*100% -> 0.042535 | F9: 0.049483626 | G9: =F9-E9 -> 0.0069486257
D10: =DATE(2030, 5,15) -> 47618 | E10: =0.043*100% -> 0.043 | F10: 0.051243964 | G10: =F10-E10 -> 0.0082439638
D11: =DATE(2033,8,1) -> 48792 | E11: =0.044747*100% -> 0.044747 | F11: 0.054222719 | G11: =F11-E11 -> 0.009475719
D12: =DATE(2034,4,5) -> 49039 | E12: =0.045486*100% -> 0.045486 | F12: 0.053150744 | G12: =F12-E12 -> 0.0076647439
D13: =DATE(2035,1,1) -> 49310 | E13: =0.046264*100% -> 0.046264 | F13: 0.051721444 | G13: =F13-E13 -> 0.0054574437
E14: Average Spread: | F14: 0.0071646834
D24: Average Spread: | E24: =AVERAGE(G6:G13) -> 0.0071646834
G38: n
E49: solvency | F49: default | H49: Years | I49: probability of default (%)
C50: 1 | D50: solvency | E50: =1-F50 -> 0.98572184 | F50: =2*(1-EXP(-E24)) -> 0.014278157 | H50: 1 | I50: =F50 -> 0.014278157
D51: default | E51: 0 | F51: 1 | H51: 2 | I51: =F53 -> 0.028352447
H52: 3 | I52: =F56 -> 0.042225783
C53: 2 | E53: {=MMULT(E50:F51,E50:F51)} -> 0.97164755 | F53: 0.028352447 | H53: 4 | I53: =F59 -> 0.055901033
E54: 0 | F54: 1 | H54: 5 | I54: =F62 -> 0.069381026
H55: 6 | I55: =F65 -> 0.08266855
C56: 3 | E56: {=MMULT(E50:F51,_xlfn.ANCHORARRAY(E53))} -> 0.95777422 | F56: 0.042225783 | H56: 7 | I56: =F68 -> 0.095766352
E57: 0 | F57: 1 | H57: 8 | I57: =F72 -> 0.10867714
H58: 9 | I58: =F75 -> 0.12140359
C59: 4 | E59: {=MMULT(E50:F51,E56:F57)} -> 0.94409897 | F59: 0.055901033 | H59: 10 | I59: =F78 -> 0.13394833
E60: 0 | F60: 1
C62: 5 | E62: {=MMULT(E50:F51,E59:F60)} -> 0.93061897 | F62: 0.069381026
E63: 0 | F63: 1
C65: 6 | E65: {=MMULT(_xlfn.ANCHORARRAY(E62),E50:F51)} -> 0.91733145 | F65: 0.08266855
E66: 0 | F66: 1
C68: 7 | E68: {=MMULT(_xlfn.ANCHORARRAY(E65),E50:F51)} -> 0.90423365 | F68: 0.095766352
E69: 0 | F69: 1
C72: 8 | E72: {=MMULT(_xlfn.ANCHORARRAY(E68),E50:F51)} -> 0.89132286 | F72: 0.10867714
E73: 0 | F73: 1
C75: 9 | E75: {=MMULT(_xlfn.ANCHORARRAY(E72),E50:F51)} -> 0.87859641 | F75: 0.12140359
E76: 0 | F76: 1
C78: 10 | E78: {=MMULT(_xlfn.ANCHORARRAY(E75), E50:F51)} -> 0.86605167 | F78: 0.13394833
E79: 0 | F79: 1
G134: solvency | H134: default
F135: solvency | G135: 0.98572184 | H135: 0.014278157
F136: default | G136: 0 | H136: 1

Sheet relevent data 
C3: bond data | D3: maturity date | E3: freaquency | F3: risk free proxiy | G3: YIELD(thousands) | H3: FV | I3: rate | J3: settelment | K3: Price (31 Dec 2024) | L3: cedit spread
C4: made up bond at 2035 | F4: 0.0323294 | G4: =((G5-G6)/0.5)*(8/12) +G5 -> 0.051721444 | H4: 100
C5: US29250NCC74 | D5: =DATE(2034,4,5) -> 49039 | E5: 2 | F5: 0.0320756 | G5: =YIELD(J5,D5,I5,K5,H5,E5) -> 0.053150744 | H5: 100 | I5: 0.0536 | J5: =DATE(2024,12,1) -> 45627 | K5: 100.32 | L5: =G4-F4 -> 0.019392044
C6: US29250NBF15 | D6: =DATE(2033,8,1) -> 48792 | E6: 2 | F6: 0.0318741 | G6: =YIELD(J6,D6,I6,K6,H6,E6) -> 0.054222719 | H6: 100 | I6: 0.025 | J6: =DATE(2024,12,1) -> 45627 | K6: 80 | L6: =G5-F5 -> 0.021075144
C7: US29250NBY04 | D7: =DATE(2030, 5,15) -> 47618 | E7: 2 | F7: 0.0302938 | G7: =YIELD(J7,D7,I7,K7,H7,E7) -> 0.051243964 | H7: 100 | I7: 0.062 | J7: =DATE(2024,12,1) -> 45627 | K7: 105.06 | L7: =G6-F6 -> 0.022348619
C8: US29250NBX21 | D8: =DATE(2028,5,15) -> 46888 | E8: 2 | F8: 0.0289418 | G8: =YIELD(J8,D8,I8,K8,H8,E8) -> 0.049483626 | H8: 100 | I8: 0.06 | J8: =DATE(2024,12,1) -> 45627 | K8: 103.3 | L8: =G7-F7 -> 0.020950164
C9: US29250NCA19 | D9: =DATE(2027,4,5) -> 46482 | E9: 2 | F9: 0.0285479 | G9: =YIELD(J9,D9,I9,K9,H9,E9) -> 0.048045307 | H9: 100 | I9: 0.0525 | J9: =DATE(2024,12,1) -> 45627 | K9: 100.97 | L9: =G8-F8 -> 0.020541826
C10: US29250NBW48 | D10: =DATE(2026,11,15) -> 46341 | E10: 2 | F10: 0.0286496 | G10: =YIELD(J10,D10,I10,K10,H10,E10) -> 0.049216982 | H10: 100 | I10: 0.059 | J10: =DATE(2024,12,1) -> 45627 | K10: 101.8 | L10: =G9-F9 -> 0.019497407
C11: estimate from online | D11: =DATE(2024,12, 31) -> 45657 | F11: 0.0314247 | G11: 0.0618
E15: book values | F15: value (million)
E16: asset | F16: 218973
E17: liabilities & equity | F17: 150000
C24: Interest rate | D24: 0.0314247
C25: Book value, bn | D25: 218.973
C26: Time to maturity | G26: 1.3245
C27: Exercise price, K=L, bn | D27: 150
C28: Sigma s, percent | D28: 29.66

Sheet plot for prob default
D6: Time (Years) | E6: Credit Metrics Model (%) | F6: Merton Model (%)
D7: 1 | E7: 0.014278157 | F7: ='merton '!F18 -> 2.8873171e-05
D8: 2 | E8: 0.028352447 | F8: ='merton '!F36 -> 0.0022953348
D9: 3 | E9: 0.042225783 | F9: ='merton '!F54 -> 0.011091873
D10: 4 | E10: 0.055901033 | F10: ='merton '!F72 -> 0.026677369
D11: 5 | E11: 0.069381026 | F11: ='merton '!F90 -> 0.048175415
D12: 6 | E12: 0.08266855 | F12: ='merton '!F108 -> 0.078478937
D13: 7 | E13: 0.095766352 | F13: ='merton '!F126 -> 0.10661636
D14: 8 | E14: 0.10867714 | F14: ='merton '!F144 -> 0.13581402
D15: 9 | E15: 0.12140359 | F15: ='merton '!F162 -> 0.16520512
D16: 10 | E16: 0.13394833 | F16: ='merton '!F180 -> 0.19415406
F63: #VALUE!
